{
 "id": "197",
 "title": "27 - 1998 الاحوال الشخصية - تعديل",
 "number": "27",
 "year": "1998",
 "type": "قانون",
 "category": "أخرى",
 "isAmendment": true,
 "source_url": "https://www.cocayemen.com/laws/197",
 "source_format": "pdf",
 "scraped_at": "2026-07-02T18:10:50.059Z",
 "preamble": "‫معدل بالقانون رقم ‪ 42‬لسنة ‪9111‬‬\n\n‫معدل بالقانون رقم ‪ 42‬لسنة ‪4004‬م‬\n\n‫قانون رقم (‪ )42‬لسنة ‪9111‬م‬\n\n‫بتعديل بعض مواد القرار الجمهوري بالقانون رقم(‪ )40‬لسنة ‪9114‬م‬\n‫بشأن الأحوال الشخصية‬\n‫باسم الشعب ‪:‬‬\n‫رئيس الجمهورية ‪:‬‬\n‫بعد الاطلاع على دستور الجمهورية اليمنية‪.‬‬\n\n‫وعلى القرار الجمهوري بالقانون رقم(‪)40‬لسنة ‪9114‬م بشأن الأحوال الشخصية‪.‬‬\n‫وبعد موافقة مجلس النواب‪.‬‬\n\n‫(أصدرنا القانون الآتي نصه)‪-:‬‬\n‫مادة (‪ : (9‬تعدل المواد )‪،44 ،49 ،40 ،46 ،42 ،91 ،92 ،92،96 ،94 ،1 ،1 ،2 ،6، 5، 2 ،4‬‬\n‫‪،51 ،91 ،42 ،61 ،66 ،56 ،51 ،54 ،54 ،59 ، 21 ، 26 ، 25 ، 24 ، 20 ،41 ،42 ،45‬‬\n‫‪، 954 ، 950 ، 924 ، 941 ،942 ،944 ، 941 ، 942 ، 940 ، 901 ، 901 ، 409 ،11‬‬\n‫‪، 402 ، 912 ، 916 ، 916 ، 519 ، 912 ، 929 ، 966 ، 569 ، 469 ،964 ، 951 ، 954‬‬\n‫‪، 441 ، 445 ،444 ،444 ،441 ، 445 ، 442 ، 444 ، 491 ،494 ،494، 499، 401‬‬\n‫‪، 424 ، 462 ،465 ،462 ،464 ،464 ،469 ، 460 ،451 ،452 ،455 ،421 ،429 ،420‬‬\n‫‪، 402 ، 404 ، 409 ،411 ، 411 ،412 ،415 ، 414 ،411 ،411 ،412 ،419 ،422 ،425‬‬\n‫‪)422 ،420 ،441 ، 442 ، 444 ،449 ، 441 ،441 ،446، 442 ،492‬من القرار الجمهوري‬\n\n‫بالقانون رقم (‪ )40‬لسنة ‪4119‬م بشأن الأحوال الشخصية على النحو التالي ‪:‬‬\n‫الكتاب الأول‬\n\n‫ِ‬\n‫الخطبة وعقد الزواج‬\n‫الباب الأول‬\n‫ِ‬\n‫الخطبة‬\n‫مادة (‪ : )4‬الخطبة هي التقدم من الراغب أو من يقوم عنه إلى ولي المرأة لطلب التزوج بها وتحرم خطبة‬\n‫المسلم على أخيه المسلم إلا أن يأذن له أو يترك كما تحرم في حال العدة إلا عدة البائن تعريضاً‪.‬‬\n‫‪1‬‬\n\n‫مادة (‪ -9 : ) 2‬لكل من الخاطبين العدول عن الخطبة‪.‬‬\n‫‪-4‬‬\n\n‫إذا كان العدول من جانب المخطوبة وجب عليها رد الهدايا بعينها إذا كانت قائمة والا فمثلها أو‬\n\n‫قيمتها يوم القبض ‪ ،‬واذا كان العدول من جانب الخاطب فلا يجب إعادة الهدايا إليه‬\n‫‪-4‬‬\n\n‫إذا أنتهت الخطبة بالوفاة أو بسبب لا يد ألحد الطرفين فيه أو بعارض حال دون الزواج فلا يسترد‬\n\n‫شئ من الهدايا المستهلكة عادة‪.‬‬\n\n‫مادة (‪ : )5‬إذا ترتب على العدول عن الخطبة ضرر يتحمل المتسبب ما ترى المحكمة لزومه ومقداره من‬\n‫التعويض إن ترافعا‪.‬‬\n‫الباب الثاني‬\n‫عقد الزواج‬\n\n‫الفصل الأول‬\n‫انعقاد الزواج وأركانه وشروطه‬\n‫مادة (‪ : )6‬الزواج هو ارتباط بين زوجين بعقد شرعي تحل به المرأة للرجل شرعاً وغايته تحصين الفروج‬\n\n‫وانشاء أسرة قوامها حسن العشرة‪.‬‬\n\n‫مادة (‪ : )2‬يشترط لصحة العقد ما يلي‪:‬‬\n‫‪-9‬‬\n\n‫أن يكون في مجلس واحد‪.‬‬\n\n‫‪-4‬‬\n\n‫إيجاب بما يفيد التزوج عرفاً من ولي للمعقود بها‪ ،‬مكلف ‪ ،‬ذكر ‪ ،‬غير محرم‪ ،‬أو بإجازته أو من‬\n\n‫وكيله‪.‬‬\n‫‪-4‬‬\n\n‫قبول التزوج قبل الإعراض من زوج مكلف غير محرم أو ممن يقوم مقامه شرعاً أو بإجازته‪.‬‬\n\n‫‪-5‬‬\n\n‫أن يكون الإيجاب والقبول منجزين ومتطابقين وغير دالين على التوقيت بمدة‪ ،‬ويلغى كل شرط لا‬\n\n‫‪-2‬‬\n\n‫تعريف الزوجين حال العقد باسم أو لقب أو إشارة أو نحو ذلك مما يميزهما عن غيرهما‪.‬‬\n\n‫يتعلق به غرض مشروع ألحد الزوجين أو يخالف موجب العقد‪.‬‬\n‫‪-6‬‬\n\n‫خلو الزوجين حال العقد من موانع الزواج المذكورة في الفصل الثالث من هذا الباب‪.‬‬\n\n‫مادة(‪ : )1‬أركان العقد التي التتم ماهيته بدونها أربعة ‪:‬‬\n‫زوج وزوجة وهما محل العقد وايجاب وقبول‪ ،‬ويتم العقد باللفظ والكتابة وبالرسالة من الغائب في مجلس بلوغ‬\n‫الخبر ‪ ،‬ويصح العقد من المصمت والأخرس بالإشارة المفهمة‪.‬‬\n\n‫مادة (‪ : )1‬يتم العقد بحضور شاهدين عدلين مسلمين أو رجل وامرأتين يسمعان لفظ الايجاب والقبول من‬\n‫المتعاقدين بالمجلس أو الكتابة أو الرسالة أو الإشارة من الأخرس والمصمت‪.‬‬\n‫مادة (‪ : )94‬يجوز للرجل تعدد الزوجات الى أربع مع تحقق ما يلي‪:‬‬\n‫‪-9‬‬\n\n‫القدرة على العدل والاّ فواحدة‪.‬‬\n\n‫‪-4‬‬\n\n‫إشعار المرأة بأنه متزوج بغيرها‪.‬‬\n\n‫‪-4‬‬\n\n‫أن يكون للزوج القدرة على الإعالة‪.‬‬\n\n‫‪2‬‬\n\n‫مادة ( ‪ :)92‬على من يتولى صيغة العقد وعلى الزوج وعلى ولي الزوجة أن يقيدوا وثيقة عقد الزواج لدى‬\n‫الجهة المختصة في السجل المعد لذلك خلال شهر واذا قام أحد ممن تقدم ذكرهم بقيد الوثيقة كفى عن‬\n‫الآخرين ‪ ،‬على أن تتضمن وثيقة عقد الزواج المعلومات الالزمة مثل سن الزوجين وأرقام بطاقات الهوية إن‬\n‫وجدت ومقدار المهر المعجل منه والمؤجل‪.‬‬\n‫الفصل الثاني‬\n‫الوالية في الزواج‬\n‫مادة (‪ : )96‬ولي عقد الزواج هو الأقرب فالأقرب على الترتيب ‪ :‬الأب وان عال ثم الأبن وان سفل ‪ ،‬ثم الاخوة‬\n‫‪ ،‬ثم أبناؤهم ‪ ،‬ثم الأعمام ‪ ،‬ثم أبناؤهم ‪ ،‬ثم أعمام الأب ‪ ،‬ثم أبناؤهم ‪ ،‬كذلك ويقدم من تكون قرابته ألب وام‬\n\n‫واذا تعدد من هم في درجة واحدة كانت الوالية لكل منهم ‪ ،‬ويصح عقد من سبق منهم مع رضاها به ويبطل‬\n‫عقد من تأخروا إذا عقدوا ألكثر من شخص واحد في وقت واحد واذا أشكل ذلك بطل العقد ‪ ،‬إلاَّ إذا ارتضت‬\n‫أحد هذه العقود صح وبطل غيره‪.‬‬\n‫مادة (‪ : )92‬القاضي ولي من لا ولي له ‪ ،‬واذا ادعت امرأة مجهولة النسب بأن لا ولي لها مع عدم المنازع‬\n‫صدقت بعد بحث القاضي والتأكد بيمينها‪.‬‬\n‫مادة (‪ - 9 :)91‬إذا كان الولي الأقرب مخالفاً في الملة أو مجنوناً أو تعذر الاتصال به أو ُخفي مكانه‬\n‫انتقلت الوالية لمن يليه‪.‬‬\n\n‫‪-4‬‬\n\n‫إذا عضل ولي المرأة أمره القاضي بتزويجها فان امتنع أمر القاضي من يليه من الأولياء الأقرب‬\n\n‫فالأقرب بتزويجها فإن فقدوا أو عضلوا زوجها القاضي بكفء ومهر مثلها‪.‬‬\n‫‪-4‬‬\n\n‫لا يقبل قول المرأة فيما ذكر في الفقرتين السابقتين من هذه المادة الا ببرهان‪.‬‬\n‫الفصل الثالث‬\n‫في موانع الزواج‬\n\n‫مادة ( ‪ : )42‬يحرم على المرء من النسب أصوله وفروعه ونساؤهم ومن تناسل من أبويه وأول درجة من‬\n\n‫نسل أجداده وجداته وان علون وأصول زوجته لمجرد العقد عليها وفروعها بعد الدخول بها‪.‬‬\n‫مادة (‪ : )46‬يحرم على الرجل الزواج من ‪:‬‬\n\n‫‪-9‬‬\n\n‫المخالفة في الملة ما لم تكن كتابية‪.‬‬\n\n‫‪-4‬‬\n\n‫المرتدة عن دين الإسالم‪.‬‬\n\n‫‪-4‬‬\n\n‫المتزوجة بغيره‪.‬‬\n\n‫‪-4‬‬\n\n‫المالعنة ممن العنها‪.‬‬\n\n‫‪-2‬‬\n\n‫المطلقة منه ثالثاً قبل أن تدخل بزوج آخر وتعتد منه‪.‬‬\n\n‫‪-5‬‬\n\n‫المعتدة إلاّ ممن تعتد منه في طالق رجعي أو بينونه صغرى في الخلع بعد عقد‪.‬‬\n‫‪3‬‬\n\n‫‪-6‬‬\n\n‫المحرمة بحج أو عمرة‪.‬‬\n\n‫‪-2‬‬\n\n‫الخنثى المشكل‪.‬‬\n\n‫‪-1‬‬\n\n‫امرأة المفقود قبل الحكم بارتفاع الزواج‪.‬‬\n‫الباب الثالث‬\n‫في أحكام الزواج‬\n‫الفصل الأول‬\n‫أحكام عامه‬\n\n‫مادة (‪ : )40‬كل زواج استوفى أركانه وشرائطه المبينة في الباب السابق فهو صحيح ولو لم يعقبه دخول ‪،‬‬\n\n‫وتترتب عليه منذ انعقاده جميع أثار الزواج المنصوص عليها في هذا القانون ما لم يكن موقوفاً حقيقة ‪،‬‬\n\n‫ويعتبر الزواج موقوفاً قبل الرضاء ممن يملكه واذا تم الرضاء سرت أثار الزواج من وقت العقد ‪ ،‬أما الموقوف‬\n‫مجا اًز وهو العقد على الصغير والمجنون فتترتب آثاره من عند العقد ولهما فسخة عند البلوغ أو الإفاقة‬\n\n‫مادة (‪ : )49‬الزواج الذي لم يستوف أركانه وشرائطه المبينة في الباب السابق باطل ولا تترتب عليه قبل‬\n‫الدخول أية أثار ‪ ،‬ويجب التفريق بين الطرفين قضاء أن لم يكن قد تم برضاهما ما لم يكن الشرط المفقود في‬\n\n‫العقد جائ اًز في مذهبيهما أو دخال فيه جاهلين ولم يخرق الاجماع المعتبر في الحالين‪.‬‬\n‫الفصل الثاني‬\n‫المهر‬\n\n‫مادة (‪ -9 : )44‬يلزم المهر للمعقود بها بعقد صحيح وهو ما حصل عليه التراضي معيناً مالاً يصح لهما‬\n‫تملكه أو منفعة غير محرمة فإذا لم يسم أو سمي تسمية غير صحيحة أو نسي ما سمي بحيث لم يعرف‬\n\n‫وجب مهر المثل‪.‬‬\n‫‪-4‬‬\n\n‫المهر ملك للمرأة تتصرف فيه كيفما شاءت ولا يعتد بأي شرط مخالف‪.‬‬\n\n‫مادة (‪ : )45‬يجب المهر كله بالدخول الحقيقي ويستحق بموت الزوجين أو أحدهما ولو قبل الدخول‪.‬‬\n‫مادة (‪ : )42‬اذا لم يسم المهر أو سمى تسمية غير صحيحة فللمرأة المطلقة قبل الدخول متعة مثلها من‬\n‫مثله بما لا يزيد على نصف مهر المثل‪.‬‬\n\n‫مهر ويسلم ما لم يؤجل‬\n‫مادة (‪ : )41‬يجوز للمرأة قبل الدخول أن تمتنع على الدخول الى أن ُي َس َّمى لها ٌ‬\n‫برضاها فإذا أجل لمدة معلومة فليس لها الامتناع قبل حلول الأجل مع مراعاة المادة ( ‪ )42‬من هذا‬\n\n‫القانون‪.‬‬\n\n‫الفصل الثالث‬\n‫في العشرة الحسنه‬\n‫‪4‬‬\n\n‫مادة (‪ :) 20‬للزوج على الزوجة حق الطاعة فيما يحقق مصلحة الأسرة على الأخص فيما يلي‪:‬‬\n‫‪-9‬‬\n\n‫الانتقال معه إلى منزل الزوجية ما لم تكن قد اشترطت عليه في العقد البقاء في منزلها أو منزل‬\n\n‫‪-4‬‬\n\n‫تمكينه منها صالحه للوطء المشروع‪.‬‬\n\n‫‪-4‬‬\n\n‫امتثال أمره في غير معصية والقيام بعملها في بيت الزوجية مثل غيرها‪.‬‬\n\n‫أسرتها فيكون عليها تمكينه من السكن معها والدخول عليها‪.‬‬\n\n‫‪-2‬‬\n\n‫عدم الخروج من منزل الزوجية الاّ باذنه أو لعذر شرعي او ما جرى العرف بمثله مما ليس فيه‬\n\n‫الاخلال بالشرف ولا بواجباتها نحوه وعلى الاخص الخروج في اصلاح مالها أو أداء وظيفتها المتفق عليها‬\n‫والتي لا تتنافى مع الشرع ويعتبر عذ اًر شرعياً للمرأة خدمة والديها العاجزين وليس لهما من يقوم بخدمتهما‬\n\n‫أو أحدهما غيرها‪.‬‬\n\n‫مادة (‪ - 9 :) 24‬يشترط في المسكن الشرعي أن يكون مستقالً تأمن فيه الزوجه على نفسها ومالها ‪،‬‬\n\n‫ويعتبر في ذلك حال الزوج ومسكن أمثاله وعرف البلد وعدم مضارة الزوجه ‪ ،‬وللزوج أن ُي ّس ّكن مع زوجته‬\n\n‫أولاده منها ومن غيرها ولو كانوا بالغين وأبويه ومحارمه من النساء اذا كان اسكانهم واجباً عليه بشرط‬\n\n‫اتساع المسكن لسكناهم وعدم مضارة الزوجه ‪ ،‬وان لا تكون قد اشترطت غير ذلك عند العقد‪.‬‬\n‫‪-4‬‬\n\n‫لا يحق للزوج أن ُي َس َّكن مع زوجته ضره لها في مسكن واحد ‪ ،‬الاّ اذا رضيتا بذلك ويحق لها العدول‬\n\n‫متى شاءت‪.‬‬\n\n‫الكتاب الثاني‬\n‫إنحالل الزواج وأحكامه‬\n‫الباب الأول‬\n‫فسخ الزواج‬\n‫مادة (‪:)25‬لا ينفسخ الزواج بفسخ أحد الزوجين لألخر بعيب من العيوب ونحوها من الأسباب المختلف في‬\n‫ثبوت الفسخ بها إلاّ بحكم المحكمة ولا يترتب على الفسخ شيء قبل الحكم به فإذا حكم بالفسخ وكان بعد‬\n‫الدخول وجبت العدة أو الاستبراء من حين الحكم به‪.‬‬\n\n‫مادة (‪ :)26‬اذا تبين بين الزوجين سبب من الأسباب القاطعة بالتحريم إنفسخ النكاح بينهما بحكم الشرع‬\n\n‫دون حاجة الى الحكم بالفسخ على أن تدون القضية بنظر المحكمة ‪ ،‬أما اذا انكر أحدهما وجود السبب‬\n‫المحرم فالبد من إثباته بحكم من المحكمة‪.‬‬\n\n‫مادة (‪ :) 21‬اذا أسلم الزوج وكانت الزوجه غير كتابيه وأبت الاسالم أو أسلمت هي وأبى الزوج الاسالم في‬\n‫مدة عدتها أو إرتد أحد الزوجين عن الاسالم إنفسخ النكاح بينهما في جميع الصور‪.‬‬\n‫مادة (‪ :)59‬لزوجة المعسر عن الإنفاق المتمرد عن الكسب وهو قادر عليه أو العاجز عنه الفسخ اذا أمتنع‬\n‫عن الطلاق‪.‬‬\n\n‫‪5‬‬\n\n‫مادة (‪ - 9 :)54‬لزوجة الغائب في مكان مجهول أو خارج الوطن فسخ عقد نكاحها بعد انقضاء سنه واحدة‬\n‫لغير المنفق وبعد سنتين للمنفق ‪ ،‬على أن تنصب المحكمة الأقرب فالأقرب ليتمكن من إعلان الغائب في‬\n‫محل معلوم في ظرف شهر بأي وسيلة‪.‬‬\n‫‪-4‬‬\n\n‫لزوجة المحكوم عليه نهائي ًا بعقوبة الحبس مدة لا تقل عن ثلاث سنوات طلب فسخ عقد نكاحها ولا‬\n\n‫يحكم لها بذلك إلاّ إذا مضى على حبس الزوج مدة لا تقل عن سنة‪0‬‬\n\n‫مادة (‪ :)54‬اذا كان الرجل متزوجاً بأكثر من واحدة مع عدم القدرة على الإنفاق والسكن فلكل منهن طلب‬\n\n‫الفسخ فإن كان له قدرة على إنفاق واسكان البعض فقط ‪ ،‬فبعد طلبهن يخيره القاضي بين إمساك من يقدر‬\n\n‫على الإنفاق عليهن واسكانهن وطالق الأخريات فإذا أمتنع فسخ القاضي زواج من طلبت‪.‬‬\n‫الباب الثاني‬\n‫الطلاق والخلع‬\n‫الفصل الأول‬\n‫الطلاق وأحكامه‬\n‫مادة (‪ :)51‬الطلاق قول مخصوص به يفك الارتباط بين الزوجين وهو إما صريح لا يحتمل غيره أو كناية‬\n‫تفتقر الى النية‪ ،‬ويقع الطلاق باللغة العربية أو بغيرها ممن يعرف معناه أو بالكتابة أو الإشارة المفهومة من‬\n‫العاجز عن النطق‪.‬‬\n‫مادة (‪ :)65‬الطال ق المعلق على فعل شئ أو تركه يقع بوقوع شرطه الذي علقه به‪.‬‬\n‫مادة (‪ :)66‬لا يقع الطلاق بالحنث بيمين الطلاق أو الحرام ويلزمه الكفارة إن لم ينو الطلاق‪.‬‬\n\n‫مادة (‪ :)61‬الطلاق البائن يزيل الزوجية حالاً فإن كان بائناً بينونة صغرى فأنه لا يمنع المطلق من الزواج‬\n\n‫بمطلقته بعقد ومهر جديدين خلال العدة في الخلع أو بعدها مطلقاً واذا كان بائناً بينونة كبرى بأن كان مكمالً‬\n‫للثالث حرمت المرأة على مطلقها مالم تتزوج بآخر يدخل بها دخو ًلا حقيقياً وتعتد منه فيجوز لألول أن‬\n‫يتزوجها بعقد ومهر جديدين‪.‬‬\n\n‫الفصل الثاني‬\n‫الخلع وأحكامه‬\n\n‫مادة (‪ :)24‬الخلع هو فرقة بين الزوجين في مقابل عوض من الزوجة أو من غيرها مالاً أو منفعة ولو كان‬\n\n‫مجهو ًلا‪.‬‬\n\n‫الباب الرابع‬\n‫الظهار والايلاء واللعان والمفقود‬\n‫الفصل الأول‬\n‫الظهار وأحكامه‬\n‫‪6‬‬\n\n‫مادة (‪ :)91‬يشترط للظهار أن يكون من زوج مكلف مسلم لزوجته التي تحته ويشترط النية في الكنايه فأن‬\n\n‫نوى غير الظهار لا تترتب أحكامه‪.‬‬\n\n‫مادة (‪:)51‬يرتفع التحريم في المطلق بالكفارة بعد إرادة الوطء واذا أتى الرجل زوجته قبل الكفارة أثم ولا يرفع‬\n‫التحريم عليه الإستمرار في الوطء حتى ُيكفر‪.‬‬\n\n‫مادة (‪ :(11‬كفارة الظهار ) عتق رقبة فأن لم يجد أو لا يستطيع العتق فصيام شهرين متتابعين فإن لم‬\n‫يستطع فإطعام ستين مسكيناً)‪.‬‬\n\n‫الفصل الثاني‬\n‫الايلاء وأحكامه‬\n\n‫مادة (‪ :)409‬يكون الإيلاء صريحاً بأن يحلف الرجل بأن لا يجامع زوجته ‪ ،‬ويكون كناية كان يحلف أن لا‬\n‫يقرب منها أو بأن لا يجمع رأسيهما وساده‪.‬‬\n\n‫الفصل الثالث‬\n‫اللعان وأحكامه‬\n‫مادة (‪:)901‬اللعان أيمان يكذب بها كل من الزوجين الآخر به يرتفع النكاح بينهما بنظر المحكمة ويوجبه‬\n‫رمي زوج مكلف مسلم لزوجته الصالحة للوطء والباقيه تحته عن نكاح صحيح أو شبهه ولو في العدة ذلك‬\n‫الرمي بزنى في حال يوجب الحد ولو أضاف الزنى إلى ما قبل العقد له بها أو لم يرمها بالزنى ولكن وقعت‬\n‫نسبة ولده منها إلى الزنا مصرحاً لا كانياً ولا بينه له ولا إقرار منه بالولد ولا منها بالزنى‪.‬‬\n\n‫مادة (‪ :)901‬يجوز لكل من الزوجين طلب اللعان لدن القاضي وعلى القاضي أن يعظهما ويحثهما على‬\n‫التصادق فأن أمتنعا بدأ بتحليف الزوج أربعاً بأن يقول ‪ :‬والله العظيم أني لصادق فيما رميتك به من الزنا‬\n\n‫ونفي ولدك هذا ‪-‬إن كان هناك ولد ‪ -‬ويزاد في الخامسة بأن لعنة الله عليه أن كان من الكاذبين ‪ ،‬ثم تحلف‬\n‫المرأة أربعاً تقول فيها ‪ :‬والله أنه لكاذب فيما رماني به من الزنا ونفي ولده هذا ‪-‬إن كان هناك ولد ‪ -‬ويزاد‬\n\n‫في الخامسة أن غضب الله عليها إن كان من الصادقين ‪ ،‬ويجب الترتيب في الحلف بحيث إذا حلفت أولاً‬\n‫وجب إعادة تحليفها بعد تحليف الزوج مالم يحكم‪.‬‬\n‫مادة (‪:)940‬إذا حكم بإعتبار المفقود ميتاً ثم ظهر حياً فأنه ‪:‬‬\n\n‫أ ‪ -‬يستحق جميع ماله‪.‬‬\n\n‫ب‪ -‬تعتبر زوجته باقية في عصمته‪.‬‬\n\n‫الكتاب الثالث‬\n‫القرابة وأحكامها‬\n‫النسب والرضاعه والحضانه‬\n‫الفصل الأول‬\n‫ثبوت النسب‬\n\n‫‪7‬‬\n\n‫مادة (‪ :)942‬يعتبر الرجل بلاغاً إذا ادعى الإحتالم مع الإحتمال وكان إبن عشر سنوات فما فوقها وتعتبر‬\n‫المرأة بالغه إذا أدعت الإحتالم مع الإحتمال وكانت بنت تسع سنوات فما فوقها وفي جميع الأحوال يعتبر‬\n\n‫الشخص بلاغاً إذا كان إبن خمس عشرة سنه فما فوقها أو ثبوت الإنبات فيهما والحيض أو الحمل في المرأة‬\n‫وعند الإختالف في إحتمال البلوغ أو في تقدير السن لعدم وجود إثبات رسمي يستعان بطبيب مختص‪.‬‬\n\n‫مادة (‪:)941‬إذا وضعت المرأة وأدعت بقاء حمل آخر ودلت القرائن على صدقها ومن القرائن قرار الطبيب‬\n‫المختص أُلحق الولد بالزوج‪.‬‬\n‫مادة (‪:)944‬إذا أتفق فراشان مترتبان فيلحق الولد بالزوج الآخر إذا أتت به لستة أشهر من يوم إمكان وطئه‬\n‫لها فإن أتت به لدون ستة أشهر الحق بالزوج الأول‪.‬‬\n\n‫الفصل الثاني‬\n‫الرضاعة وأحكامها‬\n‫مادة (‪:)942‬تستحق الأم المرضعة رزقها وكسوة مثلها من مثله بالمعروف لمدة لا تزيد على عامين من وقت‬\n‫الوالدة وتكون ديناً لا يسقط إلا بالأداء أو بالإبراء‪.‬‬\n\n‫الفصل الثالث‬\n‫الحضانة وأحكامها‬\n‫مادة (‪ :)941‬مدة الحضانة تسع سنوات للذكر واثنا عشر لألنثى ما لم يقدر القاضي خالفه لمصلحة‬\n‫المحضون مع مراعاة أحكام المادة (‪.)921‬‬\n\n‫مادة (‪ :)924‬تنتقل الحضانة من الحاضن الى من يليه بأحد أمورهي‪:‬‬\n\n‫الجنون ونحوه من المنفرات كالجذام وكذا العمى والإهمال والفسق وترك حفظ الصغير والزواج إلا أن يكون‬\n\n‫بذي رحم للصغير‪.‬‬\n‫الباب الثاني‬\n‫النفقات وأحكامها‬\n‫الفصل الأول‬\n‫نفقة الزوجة‬\n\n‫مادة ( ‪:)950‬تجب النفقة للزوجة كيف كانت على زوجها كيف كان من وقت العقد إن شرطت والاّ فمن تاريخ‬\n‫الزفاف غذاء وكساء ومسكناً وفراشا ومعالجة وأخداما والعبره بحال الزوج يس ار وعس ار وتقدم نفقة الزوجة‬\n\n‫على غيرها من النفقات‪.‬‬\n\n‫مادة (‪ :)954‬لا نفقة للزوجة في الأحوال التالية ‪:‬‬\n\n‫أ ‪ -‬إذا أمتنعت عن الإنتقال الى بيت الزوجيه من دون عذر شرعي‪.‬‬\n‫ب‪ -‬إذا تركت بيت الزوجيه من دون عذر شرعي‪.‬‬\n\n‫‪8‬‬\n\n‫ج‪ -‬إذا عملت خارج البيت دون موافقة زوجها مع مراعاة أحكام المادة (‪.) 20‬‬\n\n‫د ‪ -‬إذا أمتنعت من السفر مع زوجها دون عذر مع مراعاة أحكام المادة(‪.) 20‬‬\n‫مادة (‪ :)954‬لا يسقط حق الزوجه في الماضي بالمطل ولا في المستقبل بالإبراء ويعتبر تعجيل النفقة‬\n‫للزوجه تمليكاً لها فيما أستهلكته وأستيفاءاً للنفقة بقدرها ويجوز للزوجة إبراء الزوج مما أستحقته من النفقة‬\n\n‫في الماضي واذا تبرع شخص بنفقة الزوجة فلا تسقط إلا إذا كان المتبرع عن الزوج‪.‬‬\n‫الفصل الثاني‬\n‫نفقة الأقارب‬\n\n‫مادة (‪ :)951‬نفقة الولد البلاغ العاقل المعسر العاجز عن الكسب أو المشغول بطلب العلم إلى الثانوية العامة‬\n‫أو ما في مستواها بشرط أن لا يتجاوز سن العشرين لنيلها على أبيه أن كان موس اًر‪ ،‬فإن كان معس اًر فعلى‬\n\n‫الأم أن كانت موسرة إلا أن يكون له ولد موسر فنفقته على ولده الموسر ‪ ،‬وحكم نفقة البنت البلاغة المعسرة‬\n‫ولو كانت قادرة على الكسب ولكنها لا تتكسب إذا كانت غير متزوجة حكم نفقة الصغير المبين في المادة‬\n\n‫السابقة‪.‬‬\n‫مادة (‪:)469‬تلزم نفقة زوجة الأب المعسر على أبنه الموسر واذا تعددت زوجات الأب فلا تلزم الأبن غير‬\n‫نفقة واحدة منهن‪..‬ويجب على الأبن الموسر أن يسعف أباه المعسر بزوجة خاصة إذا كان الأب مزمناً أو‬\n\n‫مريضاً يحوجه ذلك الى زوجه تقوم بشأنه أو خادم يخدمه أو كليهما وجبت نفقة الزوجة أو الخادم على ولده‬\n\n‫الموسر‪.‬‬\n\n‫مادة (‪:)469‬لألب المعسر أن يستنفق من مال ولده الصغير والمجنون بقدر حاجته ولو بالبيع دون إذن‬\n‫القاضي إلا في العقار ونحوه فلا بد من أذن القاضي وليس لألب أن يأخذ من مال أبنه البلاغ حاض اًر أو غائباً‬\n‫أن لم يتمرد عن إنفاقه إلا بأذن القاضي إن دعت الضرورة‪.‬‬\n\n‫مادة (‪ :)569‬تسقط نفقة القريب عن المدة الماضية بعدم المطالبة ممن تلزمه النفقة إلا إذا كان المنفق‬\n‫عليه والداً أو ولداً صغي اًر أو مجنوناً‪.‬‬\n\n‫مادة (‪ :)966‬في حكم النفقة يعتبر الشخص موس اًر إذا كان يملك من المال زائداً على ما يكفيه هو ومن‬\n\n‫تلزمه نفقته ممن هو أخص من القريب المعسر الى وقت الدخل الدائم الذي يدخل عليه من وظيفة أو غلة أو‬\n‫تجارة أو صناعة وينفق على القريب المعسر من الزيادة وأن لم يكن له دخل دائم فإلى الحول ينفق من‬\n\n‫الزيادة على كفاية الحول ويعتبر الشخص معس اًر إذا كان عكس ما سبق ولا يلزمه إعطاء القريب إلا إذا لم‬\n\n‫يبق له قوت يوم وليله‪.‬‬\n\n‫الكتاب الرابع‬\n‫الهبة ومشتبهاته‬\n‫الباب الأول‬\n‫في الهبة‬\n‫الفصل الأول‬\n‫‪9‬‬\n\n‫أركان الهبة وشروطها‬\n\n‫مادة (‪ :)929‬تكون الهبة بإيجاب من الواهب أو نائبه وقبول من الموهوب له أو نائبه قبل الأعراض ولا‬\n‫يشترط في الإيجاب والقبول أن يكونا صريحين أو في مجلس واحد وانما يشترط التراضي صراحة واضحة أو‬\n‫ضمناً بما تدل عليه قرائن الأحوال ‪ ،‬وتصح الهبة بالكتابة وبالرسالة والإشارة المفهمة من أخرس ‪ ،‬ولا تتم‬\n‫الهبة إلا بقبول الموهوب له أو نائبه ويقوم القبض مقام القبول‪.‬‬\n‫الفصل الثاني‬\n‫أحكام الهبة وأثارها‬\n‫مادة (‪:)912‬إذا تمت الهبة مستوفية أركانها وشروطها المبينة في الفصل السابق فهي صحيحة ويترتب‬\n‫عليها آثارها من تملك الموهوب له المال الموهوب و إستباحة المنفعة في الحال والتزامه بأداء العوض مالاً‬\n‫أو منفعة أو غيرها إن كانت بعوض مع مراعاة ما نص عليه في المواد التالية‪.‬‬\n‫مادة (‪:)519‬الهبة في مرض الموت وما في حكمه كالمبارز ‪ ،‬ومن خرج لمالقاة العدو ومن أصيب في حادث‬\n‫مهلك تأخذ حكم الوصية ‪ ،‬ومرض الموت هو المرض المخوف المتصل بالوفاة‪.‬‬\n‫مادة (‪:)916‬الهبة للوارث ووارثه في حياته تأخذ حكم الوصية إلاّ فيما أستهلكه الموهوب له في حياة الواهب‬\n‫حقيقة أو حكما مع مراعاة أحكام المادة (‪.)419‬‬\n\n‫الفصل الثالث‬\n‫الرجوع في الهبة التبرعية‬\n‫شروطه ‪ ،‬وأحكامه‬\n‫مادة (‪:)916‬لا يجوز الرجوع في الهبة التبرعية إلاّ في الأحوال الآتية ‪:‬‬\n\n‫‪ - 9‬أن تكون الهبة التبرعية لغرض مصلحة ظاهر أو مضمر تدل عليه قرائن الحال وتعذر تحقيق الغرض‪.‬‬\n‫‪ -4‬أن يكون الواهب أباً أو أماً للموهوب له‪.‬‬\n\n‫‪ -4‬أن يكون للواهب عذر تحقق بعد الهبة بأن أصبح فقي اًر عاج اًز عن الكسب مالم يكن الموهوب له قد قبل‪.‬‬\n‫مادة (‪:(912‬مع مراعاة ما جاء في المادة )‪ )916‬من هذا القانون يشترط لصحة الرجوع في الهبة التبرعية‬\n‫التي لا غرض فيها ما يأتي ‪:‬‬\n‫‪-9‬‬\n‫‪-4‬‬\n\n‫بقاء الموهوب له على قيد الحياة‪.‬‬\n\n‫أن لا يكون قد أستهلك الموهوب في يد الموهوب له حقيقة أو حكماً كأن يكون قد تصرف به للغير‬\n\n‫فإن بقي البعض صح الرجوع فيه مع تحقق باقي الشروط‪.‬‬\n\n‫‪-4‬‬\n\n‫أن لا يكون قد زاد الموهوب زيادة متصلة لا يتسامح بمثلها والا فلا رجوع إلاّ مع تعويض الموهوب له‬\n\n‫‪-2‬‬\n\n‫أن لا يكون قد تعلق بالمال الموهوب ضمان أو رهن بدين والاّ توقف نفوذ الرجوع على إجازة صاحب‬\n\n‫بقيمة الزيادة‪.‬‬\n\n‫الضمان أو الرهن أو إلى الوفاء بما لهما من ضمانه أو دين‪.‬‬\n\n‫‪11‬‬\n\n‫‪-5‬‬\n\n‫إذا أمتنع الرجوع لعدم توفر هذه الشروط فإن كان للواهب ورثه غير الموهوب له ولم يعطهم ما توجبه‬\n\n‫المساواة وجب عليه التسوية بحسب الميراث فإن لم يفعلها أو تعذرت لزم إحتساب ذلك المال الموهوب من‬\n‫ميراث الموهوب له بعد وفاة المؤرث‪.‬‬\n‫الباب الثالث‬\n‫المشتبهات بالهبة وأحكامها‬\n‫الفصل الثاني‬\n‫في الصدقة‬\n‫مادة (‪ :)402‬تصح الصدقة لقضاء دين على الميت أو بكفنه ويقبض الدائن الدين والمجهز الكفن‪.‬‬\n‫الفصل الثالث‬\n‫النذر‬\n\n‫مادة (‪ :)401‬يشترط في الناذر أن يكون مكلفاً مختا اًر وأن يكون مسلماً عند الوفاء بنذره وان كان عند النذر‬\n\n‫كاف اًر‪.‬‬\n\n‫مادة (‪:)499‬يشترط في المال المنذور به أن يكون مملوكاً للناذر حال النذر هو أو سببه وأصله ويصح‬\n‫تعليق تعيينه بالذمة‪.‬‬\n\n‫اء أكان حال الصحة أو حال المرض مشروطاً أو غير مشروط‬\n‫مادة(‪:)494‬النذر ينفذ من ثلث المال مطلقاً سو ً‬\n‫مالم يكن قد أخرجه في حياته مخرج التصرف‪.‬‬\n\n‫مادة(‪ :)494‬لا يجوز الرجوع في النذر وانما يبطل برده من المنذور له أو من يقوم مقامه عند تحقق‬\n‫المصلحة بالرد‪.‬‬\n‫مادة(‪ :)491‬إذا نذر على المسجد ولم يعين تعين في المسجد الذي أعتاد الصالة فيه فإن لم يعتد مسجداً‬\n‫معيناً فألحوج مسجد في منطقته ثم في المسجد المشهور لكثرة صالة الناس فيه‪.‬‬\n‫الفصل الرابع‬\n\n‫العمرى والرقبى‬\n\n‫مادة (‪ :)444‬العمرى المؤقتة بمدة غير العمر تعتبر عارية وتأخذ حكم العارية وشروطها لا المقيدة بالعمر‬\n‫كأعمرتك أو أرقبتك الدار عمرك أو ما عشت فحكمها موروثة كالمطلقة‪.‬‬\n\n‫مادة (‪:)442‬الرقبى كالعمرى مطلقة أو مؤبدة أو مقيدة تأخذ أحكامها المبينة في المواد السابقة‪.‬‬\n‫الفصل الخامس‬\n‫الإختالف في الهبة‬\n‫مادة (‪:)445‬إذا أختلف الواهب والموهوب له تتبع الأحكام الآتية‪:‬‬\n‫أولاً ‪ :‬القول لمن يدعى صحة الهبة له ولوارثة‪ ،‬إلا في حالتين ‪:‬‬\n‫‪11‬‬\n\n‫‪-9‬‬\n\n‫أن يدعى الواهب فسادها لصغر أو أنه كان لا يعلم بلوغه وقت تمام الهبة لو تصادقا على وقت‬\n\n‫متقدم تمت فيه الهبة‪.‬‬\n‫‪-4‬‬\n\n‫أن يدعي الواهب فسادها لزوال عقله وكانت ظواهر الحال تغلب ذلك ‪ ،‬فالقول في هاتين الحالتين‬\n\n‫للواهب‪.‬‬\n‫ثانياً ‪ :‬القول للموهوب له في نفي شرط العوض مطلقاً‪.‬‬\n\n‫ثالثاً ‪ :‬القول للموهب له في نفي إرادة الواهب العوض في الموهوب‪.‬‬\n\n‫رابعاً ‪ :‬القول للموهوب له في أن ثمرة الموهوب حصلت بعد نفوذ الهبة إلا لقرينه قاضية فيكون القول‬\n‫للواهب‪.‬‬\n\n‫خامساً ‪ :‬القول للموهوب له في أنه قبل الهبة‪.‬‬\n\n‫الكتاب الخامس‬\n‫الوصية‬\n‫الباب الأول‬\n\n‫أركان الوصية وشروطها ومبطالتها‬\n‫وأحكامها ‪ ،‬والرجوع فيها والوصية الواجبة‬\n‫الفصل الأول‬\n‫أركان الوصية وشروطها‬\n‫مادة (‪:)441‬تنعقد الوصية باللفظ أو بالكتابة وعند العجز بالإشارة المفهمة وتتم فيما لا محظور فيه ولا حيلة‬\n‫بقبول الموصى له ويجب الإشهاد عليها إذا كانت تتعلق بحقوق تتعرض للضياع إلا أن تكون بخط الموصى‬\n\n‫المعروف‪.‬‬\n‫مادة (‪:)444‬يشترط في الموصى به ‪:‬‬\n‫‪-9‬‬\n\n‫أن يكون ما ًلا له قيمة ‪ ،‬أو منفعة لها أجره‪.‬‬\n\n‫‪-4‬‬\n\n‫أن يكون في حدود ثلث التركه إذا كان للموصي ورثه‪.‬‬\n\n‫‪-4‬‬\n\n‫أن يكون موجوداً ومملوكاً للموصي عند موته‪.‬‬\n\n‫الفصل الثاني‬\n‫مادة (‪ :)444‬تبطل الوصية بأمور هي ‪-:‬‬\n‫‪-9‬‬\n‫‪-4‬‬\n\n‫مبطالت الوصية‬\n\n‫تلف العين الموصى بها قبل وفاة الموصي‪.‬‬\n\n‫رد الموصى له الوصية بعد وفاة الموصي طبقاً للمادة (‪ )451‬من هذا القانون‪.‬‬\n\n‫‪-4‬‬\n\n‫موت الموصى له أو إكتشاف موته قبل وفاة الموصي‪.‬‬\n\n‫‪-2‬‬\n\n‫موت الموصى له مع الموصي في وقت واحد بحيث لا يعرف من منهما مات أولاً‪.‬‬\n‫إنقضاء وقت الوصية المؤقتة في المنافع لا في الأعيان فيلغى التوقيت ويؤبد‪.‬‬\n\n‫‪-5‬‬\n\n‫‪12‬‬\n\n‫‪-6‬‬\n\n‫رجوع الموصي عما أوصى به قوالً أو فعالً طبقاً للمادة (‪ )451‬من هذا القانون‪.‬‬\n\n‫‪-1‬‬\n\n‫إذا كان الموصي مديناً بدين يستغرق كل ماله‪.‬‬\n\n‫‪-2‬‬\n\n‫قتل الموصى له الموصي عمداً أو بشهادة زور أدت إلى قتله إلا إذا تقدمت الجناية الوصية‪.‬‬\n\n‫‪-1‬‬\n\n‫رجوع المجيز عن إجازة تمت في حياة الموصي‪.‬‬\n‫الفصل الثالث‬\n‫أحكام الوصية‬\n‫الفرع الأول‬\n‫أحكام تتعلق بالموصى له‬\n\n‫مادة (‪:)445‬لا تصح الوصية لوارث الوارث في حياة مورثه إلا لمبرر يعوقه عن التكسب كالأعمى والأشل‬\n‫وأمثالهما مع الفقر‪.‬‬\n\n‫مادة (‪:)441‬لا تصح الوصية إلا لمعين ‪ ،‬شخصاً كان أو جهة عامة ‪ ،‬أو خاصة‪.‬‬\n\n‫مادة (‪:)420‬تصح الوصية لمختلف الملة من الكتابيين غير الحربى فيما لم يكن محظو اًر‪.‬‬\n\n‫مادة (‪:)429‬الإيصاء بأفضل أنواع البر يحمل على الجهاد أو على العلم أو سائر المبرآت والمرجع هو‬\n‫الظروف ومقتضيات الأحوال‪.‬‬\n‫مادة (‪:)421‬إذا أوصى بأرض وعينها بإشارة أو لقب يحج عنه بثمنها فإن الغلة قبل البيع للورثة‪.‬‬\n‫الفرع الثالث‬\n‫تزاحم الوصايا‬\n‫مادة (‪:)455‬إذا تزاحمت الوصايا التبرعية فتعتبر من الثلث ويقسم بينها‪.‬‬\n‫الفصل الرابع‬\n‫الرجوع عن الوصية وردها وقبولها‬\n‫مادة (‪ :)452‬للموصى إلى حين موته الرجوع عن الوصية قوالً أو فعالً كما إذا تصرف في العين الموصى بها أو هدمها أو غير‬\n‫معالمها ‪ ،‬ولا يعتبر تغيير أسم العين الموصى بها أو صفاتها رجوعاً‪ .‬واذا أضاف الموصي إلى العين الموصى بها دون ان‬\n\n‫تتغير معالمها إشترك الورثة مع الموصى له بقدر ما تناولته الإضافة‪ .‬والتصرف المنجز لا رجوع فيه إلا أن يكون في مرض‬\n\n‫الموت أو كانت فيه حيلة فيأخذ حكم الوصية‪.‬‬\n\n‫مادة (‪ :)451‬للموصي له رد الوصيه أو قبولها بعد موت الموصي لا قبله ولا يصح الرجوع عن القبول إلا بإحدى طرق التمليك‬\n‫‪ ،‬واذا علم الموصى له بالوصية بعد وفاة الموصي ولم يحضر عند حصر الأموال أو قسمتها ولا وكل عنه وطلبه الوارث عند‬\n\n‫القاضي فامتنع عن الحضور بغير عذر حكمت المحكمة باعتباره راداً للوصية ويقوم وصي القاصر والمجنون أو وليهما عنهما‬\n‫في رد الوصية وقبولها ويلزم أذن القاضي لرد الوصية وفي كليهما تراعى المصلحة‪.‬‬\n\n‫الفصل الخامس‬\n‫الوصية الواجبة‬\n\n‫‪13‬‬\n\n‫مادة (‪:)460‬تجب التسوية بين الأولاد في الزواج والتعليم فإذا كان قد صرف أموالاً في تزويج وتعليم البعض‬\n‫سوى القاضي بينهم بإخراج القدر المساوي‬\n‫فعليه تسوية الآخرين بهم فإن لم يفعل حتى مات ولم يوص بها َّ‬\n‫لهم مع وجوب التسوية أيضاً بين الأولاد وبقية الورثة إن كانوا طبق طريقة المواريث‪.‬‬\n‫الباب الثاني‬\n\n‫في الوصي‬\n‫الفصل الأول‬\n‫تعريف الوصي وشروطه‬\n‫مادة (‪ :)469‬الوصي هو الذي يقيمه المورث في تركته لتنفيذ وصاياه أو لقضاء ديونه أو إستيفائها أو لرعاية قصارة وأموالهم‬\n‫أو لكل ذلك ويجوز للوصي ان يوصي غيره فيما هو وصي فيه فيقوم وصيه مكانه بعد موته‪.‬‬\n\n‫مادة (‪ :)464‬الوصي مقدم على القاضي واذا مات ولم يوص ففي رعاية الصغار وأموالهم يقدم الأب ثم‬\n‫وصيه ثم الجد ثم وصيه ثم القاضي‪.‬‬\n\n‫مادة (‪ :(464‬تعين المحكمة منصوباً )وصياً( لمن لا وصي له ولا ولي مع مراعاة أحكام المادة )‪.)464‬‬\n\n‫مادة (‪ :)462‬إذا توفى الوصي أو حجر عليه أو أفلس فعلى المحكمة أن تعين منصوباً (وصياً) عن القاصر‬\n‫واذا غاب الوصي أو أعتقل وخشى من غيابه أو إعتقاله تعرض مصلحة القاصر للضياع فعلى المحكمة ان‬\n\n‫تعين منصوباً (وصياً( مؤقتاً ‪ ،‬مع مراعاة أحكام المادة )‪.)464‬‬\n\n‫مادة (‪:)564‬إذا مات المورث عن ورثة بالغين دون أن يوصي إلى أحد وعليه ديون وله حقوق فعند‬\n‫إختالف الورثة تعين المحكمة من بينهم من يقوم بهذه الواجبات ‪ ،‬واذا قبض أحد الورثة شيئاً فليس له أن‬\n\n‫يستبد به ولو بقدر نصيبه في التركة ‪ ،‬واذا أشترى الوارث بمال من التركة وطلب الورثة أشتراكهم فيه كل‬\n‫بقدر نصيبه أجيبوا إلى ذلك والا كان لهم الرجوع بعين مالهم‪.‬‬\n‫مادة (‪:)462‬المشرف والرقيب والمشروط علمه ورأيه يقتصر عملهم على الإشراف أو الرقابة أو العلم أو‬\n‫الرأي إلا إذا نص الموصي على غير ذلك‪.‬‬\n‫الفصل الثاني‬\n‫والية الوصي وأجره‬\n\n‫مادة (‪ : )424‬تثبت الوصاية للوصي بتعيين من جهة الموصي وقبول الوصي لها ‪ ،‬وتوفر شروط الوصاية‬\n‫فيه‪.‬‬\n‫مادة (‪:)524‬إذا تعدد الأوصياء فليس ألحدهم الإنفراد في غير تجهيز الميت وشراء حاجة الطفل ورد الوديعة‬\n‫وبيع ما يخاف عليه من التلف وجمع الأموال الضائعة إلا بنص من الموصي‪.‬‬\n\n‫مادة (‪:)422‬إذا أشترط الموصي إجتماع الوصيين ومات أحدهما بطلت وصاية الآخر أما إذا غاب أحد‬\n‫الوصيين أو تمرد كانت الوالية للقاضي إلى أن يجتمعا أو يعود الغائب مع مراعاة أحكام المادة (‪.)464‬‬\n\n‫‪14‬‬\n\n‫مادة (‪ : )914‬أجرة الوصي تخرج من رأس المال مطلقاً إذا كانت أجرة المثل فإذا زاد الموصي كانت الزيادة‬\n\n‫وصية فإن كانت الوصاية مختصة بشئون القاصرين وأموالهم كانت الأجرة من أنصباءهم لا من رأس المال‪.‬‬\n‫الفصل الثالث‬\n‫ما يجوز للوصي وما لا يجوز‬\n\n‫مادة (‪ :)412‬مع مراعاة ما سبق النص عليه في هذا القانون بالنسبة لألب ‪ ،‬لا يصح للوصي الانفاق على‬\n‫أب القاصر أو على من تجب على القاصر نفقته الاَّ بتقدير من القاضي‪.‬‬\n\n‫مادة (‪ :)411‬لا يجوز للوصي أن يتنازل عن دعاوى القاصر أو اسقاط حقوقه الاَّ بإذن من المحكمة مع‬\n‫تحقق المصلحة في ذلك‪.‬‬\n‫مادة (‪ :)411‬يجب على الوصي حفظ مال القاصر ‪ ،‬وكذا الحلي ونحوها في مقر أمين ‪ ،‬ويجوز له بإذن‬\n‫المحكمة إيداع النقود من مال القاصر الفاضل عن النفقات للمضاربة فيها بأحد المصارف غير الربوية‬\n\n‫بضمان‪ ،‬ولا يجوز سحب شئ منه الاّ بإذن المحكمة وللمصلحة‪.‬‬\n‫الفصل الرابع‬\n\n‫ما يجب على الوصي إبلاغ المحكمة به‬\n‫مادة (‪ :)414‬يجب على الوصي تقديم حساب للمحكمة عن ادارته ألموال القاصر مؤيداً بالمستندات كل عام‬\n\n‫ويجب عليه إيداع الفائض من واقع كشف الحساب الذي يقدمه أو ما يلزمه به القاضي نتيجة فحص الحساب‬\n‫باسم القاصر في أحد المصارف غير الربوية وللقاضي إعفاء الوصي من المحاسبة مستقبالً إذا كان مال‬\n‫القاصر لا يغل ما يفيض عن حاجته‪.‬‬\n\n‫الفصل الخامس‬\n‫فيما يضمنه الوصي‬\n‫مادة (‪:)514‬إذا اجر الوصي مال القاصر بأقل من اجر المثل ضمن مع وجود من يستأجره باجرة المثل‪.‬‬\n‫الفصل السادس‬\n‫في انتهاء وصية الوصي‬\n‫مادة (‪ :)412‬تنتهي وصاية الوصي بموته أو بعزله أو باستعفائه لعذر مقبول ما لم يتعين عليه وجوب القيام‬\n‫بالوصية أو خشي على المال تلفه ‪ ،‬وبالنسبة للقاصر أيضاً بموت القاصر او ببلوغه الرشد‪.‬‬\n\n‫مادة (‪ :)411‬متى انتهت وصاية الوصي ‪ ،‬ألزم هو او ورثته بتقديم حساب ختامي مؤيداً بالمستندات عن‬\n\n‫وصايته وبتسليم القاصر الذي بلغ رشده ما بيده من أموال ولا تبراء ذمة الوصي أو ورثته إلاَّ باعتماد‬\n‫الحساب الختامي من المحكمة أو القاصر بعد بلوغه الرشد‪.‬‬\n‫الكتاب السادس‬\n‫المواريث‬\n‫الباب الأول‬\n‫أحكام عامة‬\n\n‫‪15‬‬\n\n‫مادة (‪:)411‬يقصد بالألفاظ والتعابير التالية الواردة في هذا الكتاب المعاني الموضحة أمام كل واحد منها‪:‬‬\n‫الإرث ‪:‬‬\n\n‫هو عبارة عن انتقال الأموال والحقوق الخاصة بالميت إلى من يرثه‪.‬‬\n\n‫المورث‪ :‬هو الشخص الذي يتوفى او حكم بموته‪.‬‬\n‫الوارث ‪ :‬هو من يستحق التركة أو نصيباً منها بسبب القرابة أو الزوجية أو الوالء‪.‬‬\n\n‫المورث ‪ :‬هو عبارة عن الحقوق والأموال التي تركها الميت‪.‬‬\n‫السبب ‪ :‬هو ما يلزم من وجوده الوجود ومن عدمه العدم‪.‬‬\n‫المانع ‪ :‬هو ما يلزم من وجوده عدم الحكم‪.‬‬\n\n‫الفرض ‪ :‬هو النصيب الذي قدرته الشريعة الإسالمية للوارث لا يزيد إلاّ بالرد ولا ينقص الاّ بالعول‪.‬‬\n\n‫العاصب ‪:‬هو من ليس له سهم مقدر في التركه ويأخذ ما يفي عن سهام ذوي الفروض واذا انفرد اخذ المال كله‪.‬‬\n‫العاصب بنفسه ‪:‬هو كل ذكر لا يدخل في نسبه الى الميت انثى ولا يحتاج في التعصيب الى غيره‪.‬‬\n‫العاصب بغيره ‪:‬هو كل انثى صاحبة فرض تحتاج في التعصيب الى غيرها وتشاركه في العصوبه‪.‬‬\n\n‫العاصب مع غيره ‪ :‬هو كل انثى صاحبة فرض تحتاج في التعصيب الى غيرها ولا تشاركه في العصوبه‪.‬‬\n\n‫كل أو بعضه‪ ،‬من مقادير انصبائهم في التركة‪.‬‬\n‫الحجب ‪:‬هو منع من قام به سبب الإرث من نصيبه ٍ‬\n\n‫العول ‪:‬هو زيادة في عدد سهام ذوي الفروض ونقصان ( من مقادير) انصبائهم في التركة‪.‬‬\n\n‫الرد ‪:‬هو ضم الباقي من التركة على أصحاب الفروض غير الزوجين بنسبة فروضهم حيث لا عاصب‪.‬‬\n\n‫ذو الرحم ‪:‬المراد به كل قريب ليس بذي سهم ولا عصبة‪.‬‬\n\n‫الجد الصحيح ‪:‬هو الذي لا يتوسط بينه وبين الميت انثى(الجد العصبي)‬\n‫الجده الصحيحة ‪ :‬هي التي لا يدخل بينها وبين الميت جد غير وارث‪.‬‬\n‫الخنثى المشكل ‪ :‬هو من له آله ذكر وانثى ولم يتبين حاله‪.‬‬\n‫المفقود ‪ :‬هو الغائب الذي لم تعلم حياته ولا موته‪.‬‬\n‫ولد الزنا ‪ :‬هو المولود عن طريق السفاح‪.‬‬\n‫ولد اللعان ‪:‬هو من ولد على فراش زوجيه وانكر الزوج بنوته وحكم الحاكم بنفي نسبه‪.‬‬\n‫أصل المسألة ‪:‬هو اقل عدد يمكن أن تؤخذ منه سهام الورثة‪.‬‬\n‫التصحيح ‪ :‬هو أن يضرب أصل المسألة أو عولها في أقل عدد يمكن معه أن يستحق كل وارث بانفراده قد اًر‬\n‫من السهام برقم صحيح وحاصل الضرب هو المسألة بعد التصحيح‪.‬‬\n\n‫مادة (‪ :)904‬الإرث بالنكاح يكون بطريق الفرض أما الإرث بالنسب فيكون بطريق الفرض أو التعصيب أو‬\n\n‫بهما معاً أو بالوالء أو بالرحم عن طريق أسبابه مع مراعاة قواعد الحجب والعول والرد‪.‬‬\n\n‫مادة (‪ :)404‬يورث الأموات من بعضهم بعضا إذا كانوا متوارثين فيما بينهم مع الأحياء الوارثين من أصل‬\n\n‫أموال الأموات التي يملكونها دون الموروثة من الميت الأخر حيث لا يورث ميت مما ورثه من ميت آخر ثم‬\n\n‫يورث الأحياء لكل مما كان متروكاً لمؤرثه في الأصل ومما جاء من الميت الأخر‪.‬‬\n‫مادة (‪:)402‬المستحقون للتركة في هذا القانون ستة أصناف على النحو التالي‪:‬‬\n\n‫أ ‪ -‬أصحاب الفرض‪.‬‬\n‫‪16‬‬\n\n‫‪ -9‬البنات وبنات الابن وان نزلن‪.‬‬\n‫‪ -4‬الاخوات الشقيقات‪.‬‬\n‫‪ -4‬الاخوات ألب‪.‬‬\n‫‪ - 2‬الام‪.‬‬\n‫‪ -5‬الأخوة ألم‪.‬‬\n‫‪ -6‬الزوج والزوجة‪.‬‬\n‫‪ -2‬الجدة ألب والجدة ألم‪.‬‬\n\n‫‪ -1‬الأب وابوه وان عال في حالة المادة (‪ )449‬من هذا القانون‪.‬‬\n‫ب‪ -‬العصبات النسبية ‪-:‬‬\n\n‫‪ -9‬الذكور ‪ :‬وهم (الابن ‪ ،‬وابن الابن وان نزل‪ ،‬الأب وأبوه وان عال ‪ ،‬الأخ الشقيق ‪ ،‬والأخ ألب ‪ ،‬وابن الأخ‬\n‫الشقيق وان نزل ‪ ،‬ابن الأخ ألب وان نزل‪ ،‬العم الشقيق ‪ ،‬العم ألب ‪ ،‬ابن العم الشقيق وان بعد ‪ ،‬ابن العم‬\n‫ألب وان بعد)‪.‬‬\n‫‪ -4‬الإناث ‪( :‬البنات وبنات الابن وأن نزلن ‪ ،‬الأخوات الشقيقات ‪ ،‬الأخوات ألب كل ذلك إذا وجد معهن من‬\n‫يعصبهن)‪.‬‬\n‫ج‪ -‬ذو الأرحام‪.‬‬\n‫د ‪ -‬المقر له بنسب‪.‬‬\n\n‫ه ‪ -‬أصحاب الوصايا والديون‪.‬‬\n‫و ‪ -‬الخزانة العامة (بيت المال)‬\n‫الباب الثاني‬\n‫الفروض المقدرة وأصحابها‬\n‫مادة ( ‪:)492‬السدس ‪ :‬ويستحقه من يأتي‪-:‬‬\n‫‪ -9‬الأب اذا كان للميت فرع وارث‪.‬‬\n‫‪ -4‬الجد الصحيح اذا كان للميت فرع وارث ولم يحجب‪.‬‬\n‫‪ -4‬الأم اذا وجد للميت فرع وارث أو اثنان فأكثر من الاخوة والاخوات وهو لها في مسألة زوج وأبوين‪.‬‬\n‫‪ - 2‬بنت الابن فأكثر مع البنت الواحدة تكملة للثلثين إذا لم تعصب‪.‬‬\n\n‫‪ -5‬الأخت ألب فأكثر مع الأخت الشقيقة الواحدة تكملة للثلثين إذا ورثت ولم تعصب‪.‬‬\n‫‪ -6‬الأخ ألم أو الأخت ألم إذا كان واحداً ولم يكن للميت فرع وارث ولا أصل ذكر‪.‬‬\n‫‪ -2‬الجدة أو الجدات إذا لم يحجبن‪.‬‬\n\n‫الباب الرابع‬\n‫الحجب‬\n‫مادة ( ‪:(442‬حجب الحرمان )الإسقاط) يدخل على أحد عشر صنفاً على النحو التالي‪:‬‬\n‫‪17‬‬\n\n‫‪ -9‬يحجب ولد الابن ومن تحته من الأولاد بالابن والأعلى من أولاد الأبناء يحجب من تحته‪.‬‬\n‫‪ -4‬يحجب الجد ومن فوقه من الأجداد والجدات من قبله بالأب وكل جد قريب يحجب الجد البعيد‪.‬‬\n‫‪ -4‬تحجب الجدات من أي جهة بالأم‪.‬‬\n‫‪ - 2‬يحجب الأخ ألب وأم بالابن وابن الابن وان نزل والأب‪.‬‬\n‫‪ -5‬يحجب الأخ ألب بالابن وابن الابن وان نزل والأب والأخ ألب وأم والأخت ألب وأم إذا عصبتها البنت أو‬\n‫بنت الابن وان نزلت‪.‬‬\n‫‪ -6‬يحجب الأخ ألم بالولد وولد الابن وان نزل ذك اًر كان أو أنثى والأب والجد وان عال‪.‬‬\n\n‫‪ -2‬يحجب ابن الأخ ألب وأم بالابن وابن الابن وان نزل والاب والجد وان عال والأخ ألب وام ‪ ،‬والأخ ألب ‪،‬أو‬\n‫الأخت ألبوين ‪،‬او ألب إذا عصبتهما البنت او بنت الأبن وان نزلت‪.‬‬\n\n‫‪ -1‬يحجب ابن الأخ ألب بالابن وابن الابن وان نزل‪ ،‬والأب والجد وان عال ‪ ،‬والأخ ألب وام ‪ ،‬والأخ ألب‪،‬‬\n‫وابن الأخ ألب وام ‪ ،‬والأخت ألبوين ‪ ،‬وبالأخت ألب إذا عصبتا بالبنت ‪ ،‬أو بنت الابن وان نزلت‪.‬‬\n‫‪ -1‬يحجب الأعمام وبنوهم بالأب والجد وان عال ‪ ،‬والابن وابن الابن وان نزل والأخ الشقيق والأخ ألب وابن‬\n‫الأخ الشقيق وابن الأخ ألب أو الأخت ألبوين أو ألب إذا عصبتا بالبنت أو بنت الابن وان نزلت‪.‬‬\n‫‪ -9.‬تحجب بنات الابن بالبنتين فاكثر اذا لم يكن معهن معصب‪.‬‬\n‫‪ -99‬تحجب الأخوات ألب بالأختين ألبوين فاكثر إذا لم يكن معهن أخ معصب‪.‬‬\n‫الباب السادس‬\n\n‫في إرث ذوي الأرحام‬\n‫مادة (‪:)446‬ذوو الأرحام أربعة أصناف على النحو التالي‪:‬‬\n‫‪-4‬‬\n\n‫الصنف الأول ‪ :‬من ينتمي إلى الميت وهم ‪-:‬‬\n\n‫أ ‪ -‬اوالد البنت ذكو اًر كانوا أو إناثاً لهم ميراثها ويقسم بينهم بالسوية‪.‬‬\n\n‫ب ‪ -‬أولاد بنت الابن وأولاد بنات الابن ذكو اًر كانوا أو إناثا لهم ميراثها أو ميراثهن (النصف أو الثلثان أو‬\n‫السدس إذا كانوا مع من يدلي بالبنت)‪.‬‬\n\n‫‪-2‬‬\n\n‫الصنف الثاني ‪ :‬من ينتمي إلى أبوي الميت ‪-:‬‬\n\n‫أ ‪ -‬أولاد الأخت ألب وأم او ألحدهما لكل ميراث أمه مع الاجتماع والانفراد فرضاً ورداً‪.‬‬\n‫ب‪ -‬أولاد بنات الأخ ألب وام حكمهم حكم من يدلون بهن الى الميت اجتماعاً وانفراداً‪.‬‬\n‫ج‪ -‬بنات ابن الأخ البوين أو ألب حكمهن حكم من أدلين به‪.‬‬\n\n‫د ‪ -‬اوالد الأخ ألم حكمهم حكم من يدلون به ولهم ميراثه يقتسمونه بينهم على عدد رؤوسهم ويستوى فيه‬\n‫الذكر والانثى‪.‬‬\n‫‪-5‬‬\n\n‫الصنف الثالث ‪ :‬من ينتمي الى جد الميت او جدته وهم‪:‬‬\n\n‫أ ‪ -‬بنت العم ألب وام او ألب وبنت ابن العم ألبوين او ألب وحكمهن حكم من يدلين به من ابائهن ويعامل‬\n‫معاملتهن اوالد العم ألم واوالد العمات وعمات الأب والعمة ألم وبنات أعمام الأم وكل من يدلي بالأب‪.‬‬\n‫‪18‬‬\n\n‫اء كانت ألبوين او الحدهما ينزلون منزلة الأب‪.‬‬\n‫ب ‪ -‬العم ألم والعمة مطلقاً سو ً‬\n\n‫ج‪ -‬الأخوال والخالات ألبوين او ألحدهما وحكمهم انهم ينزلون منزلة الأم ويأخذون ما تأخذه ويقسم المال‬\n\n‫بينهم إذا انفردوا فرضاً ورداً ونصيب الأم الثلث مع عدم الحاجب أو السدس اذا كان هناك حاجب‪.‬‬\n\n‫مع مراعاة انه في حالة ما إذا اجتمع ثلاثة أخوال متفرقين فانه يكون للخال من الأم السدس والباقي للخال‬\n\n‫الشقيق ‪ ،‬أما أخوال الأب وخالاته وأخوال الأم وأعمامها وعماتها وأولادهم فينزل كل منهم منزلة ولد من‬\n\n‫يدلون به لا منزلة من يدلون من الاجداد والجدات‪.‬‬\n‫‪-6‬‬\n\n‫الصنف الرابع ‪ :‬من ينتمي إليهم الميت وهم ‪:‬‬\n\n‫أ‪ -‬أب الأم ينزل منزلة الأم‪.‬‬\n‫ب ‪ -‬أب أم الأب ينزل منزلة بنته أم الأب‪.‬‬\n\n‫ج ‪ -‬الأجداد والجدات الذين ليسوا بعصبات ولا ذوي سهام ينزلون منزلة أولادهم ولهم ميراث من ينزلون‬\n‫منزلته‪.‬‬\n‫الباب السابع‬\n‫في إستحقاق التركة للمقر له بنسب‬\n‫مادة (‪ :)441‬يستحق المقر له بنسب أو سبب التركة أو جزءاً منها إذا كان مجهول النسب ولم يقم به مانع‬\n\n‫من موانع الإرث وكان المقر له حياً حقيقة أو حكماً عند موت المؤرث ولا واسطة بينه وبين المقر به ولم يرد‬\n‫الإقرار إذا كان بلاغاً وأن يدخل الإقرار ضر اًر على المقر في ميراثه وأن يكون مكلفاً مختا اًر لم يعلم هزله ولا‬\n\n‫كذبه شرعاً ولا عقالً ‪ ،‬فان كان بينهما واسطة ولم يصدق الإقرار شارك المقر به المقر في الإرث لا في النسب‬\n‫وكانت المشاركة بقدر ما كان سينقصه من ميراثه لو ثبت نسبه‪.‬‬\n‫الباب الثامن‬\n‫في أحكام متنوعة‬\n‫مادة (‪ :)441‬يؤخر للحمل من تركة المتوفي نصيب ذكر حتى يتبين نوع الحمل ولا يرث الحمل إلاّ إذا إستهل‬\n‫بعطاس أو بكاء أو حركة تدل على الحياة ولستة أشهر على الأقل من تاريخ إمكان الوطئ مع مراعاة أنه لا‬\n\n‫حد ألكثر مدة الحمل في حال إستمرار القرائن‪.‬‬\n‫مادة (‪ :)449‬نصيب المفقود يخرج من التركة ويوقف فان ظهر حياً حقيقة أو بحكم المحكمة وقت موت‬\n\n‫المؤرث أخذه والاَّ وزع الموقوف على من يستحقه من الورثة معاشاً حتى يتبين أمره أو يصدر حكم بمضي‬\n‫العمر المقرر مدته بسبعين سنه من تاريخ والدته فيصير لمن يرثه عقب الحكم‪.‬‬\n\n‫مادة (‪ :)444‬ولد الزنا وولد اللعان يرث أمه وقرابتها وترثه هي وقرابتها‪.‬‬\n‫مادة (‪ :)442‬على متولي القسمة أن ينظر أولاً إلى سهام الورثة ويستخرج منها المخرج الجامع حسب‬\n‫تفصيل ذلك في حساب الفرائض ومنه يقسم والمخرج الجامع يخرج بطريقتين ‪:‬‬\n\n‫أ‪ -‬بطريقة القيراط وهو ما تجرى به المعاملة في اليمن والوحدة فيه أربعة وعشرون قيراطاً يقسم ولو بكسر‪.‬‬\n\n‫‪19‬‬\n\n‫ب‪-‬استخراج الوحدة الجامعة من مخارج ذوي السهام الست التي سبق تفصيلها بحيث يصير نصيب كل وارث‬\n‫جب اًر لا كسر فيه حسبما هو معروف في علم الفرائض وان كان الورثة عصبة فقط فمسألتهم تخرج من مبلغ‬\n‫عدد رؤوسهم بعد البسط للذكر مثل حظ الأنثيين‪.‬‬\n\n‫مادة (‪:(441‬كل تركة أجتمع فيها السدس والثلث والنصف ) زوج وأخوان ألم وأم) فأصل مخرجها من ستة‬\n‫وتعول إلى سبعة( زوج وأخت ألبوين وأخت ألب( أو إلى ثمانية )زوج وأم وأخت( أو إلى تسعة) زوج وأم‬\n‫وأخت وجد( أو إلى عشرة) زوج وأم واخوان ألم وأخت ألبوين وأخت ألب)‬\n‫مادة (‪:)420‬كل تركة أجتمع فيها الربع والسدس أو الثلث فاصل مخرجها من أثنى عشر (زوجة واخوان ألم‬\n‫وأم وعصبة( وقد تعول إلى ثلاثة عشر ) زوج وأم وبنت وبنت إبن( أو إلى خمسة عشر )زوج وأبوان وبنتان)‬\n‫أو إلى سبعة عشر (أم وزوجة واخوان ألم وأختان ألب وأم)‪.‬‬\n\n‫مادة (‪:)422‬المناسخة هي أن يموت وارث من الورثة أو اكثر قبل قسمة تركة المؤرث الأول فانه لا يمكن‬\n\n‫قسمة تركة الميت الثاني إلاَّ بعد قسمة الدرجة الأولى وبالاختصار فانه البد لمثل هذه المسألة من صورتين‪:‬‬\n‫‪-9‬‬\n\n‫الصورة الأولى ‪-:‬‬\n\n‫وهي إذا كان مخرج مسئلة الميت الأول موافقة لمخرج مسئلة الميت الثاني ‪ ،‬كان يتوفى شخص عن أب وأم‬\n‫وابنتين فلكل من الأب والأم السدس ومخرجها من ستة ولكل واحدة من الابنتين اثنان ثم توفيت أحد الأبنتين‬\n‫عن جدها وجدتها وأختها فمخرج هذه المسألة أيضاً من ستة وما بيد البنت من المسألة الأولى اثنان لا‬\n\n‫تنقسم على ورثتها ولكنها توافق مسألتها فتضرب نصف المسألة الثانية وهي ثلاثة في الأولى وهي ستة‬\n\n‫تصح من ثمانيه عشر ثم تستأنف التقسيم للمسألتين فلكل من الأب والأم من الأولى السدس ثالثه ولكل‬\n‫واحده من ابنتي المتوفي سته يصير تقسيم السته لورثة الابنه المتوفاه ثالثه ألختها وواحد لجدتها واثنان‬\n‫لجدها بالتعصيب‪.‬‬\n‫‪-4‬‬\n\n‫الصورة الثانية ‪-:‬‬\n\n‫اذا كان مخرج المسألة الثانية يباين مخرج المسألة الأولى كأن يتوفى شخص عن ام وابنين فالمسألة من‬\n‫سته وتصح من اثنى عشر ثم توفى احد الابنين عن ولدين وبيدهما حصة أبيهما خمسة ومسألتيهما من‬\n‫اثنين من عدد راسيهما والينقسم ما أتى لها من المسألة الأولى وهي خمسه على مسألتيهما فتضرب المسألة‬\n‫الثانية ‪،‬وهي اثنان في المسألة الأولى وهي اثنى عشر تصح من اربعه وعشرين لألم السدس ( اربعه )‬\n‫ولعمهما عشرة ولكل من الابنين في المسألة الثانيه خمسة‪.‬‬\n\n‫مادة (‪ : (4‬تحذف المادة )‪ (956‬من القرار الجمهوري بالقانون رقم )‪ )40‬لسنة ‪4119‬م بشأن الأحوال‬\n‫الشخصية‪.‬‬\n‫مادة(‪ : )4‬يعمل بهذا القرار من تاريخ صدوره وينشر في الجريدة الرسمية‪ .‬صدر برئاسة الجمهورية –‬\n‫بصنعاء ‪ ،‬بتاريخ ‪/ 2‬شعبان‪9291/‬ه ‪،‬الموافق ‪/44‬نوفمبر‪9111/‬م علي عبد الله صالح‬\n‫رئيس الجمهورية‬\n\n‫‪21‬‬\n\n21",
 "articles": []
}