{
 "id": "60",
 "title": "قانون رقم (14) لسنة 2006م بشأن الموافقة على بروتوكول بازل بشأن المسؤولية والتعويض عن الضرر الناجم عن نقل النفايات الخطرة والتخلص منها عبر الحدود",
 "number": "14",
 "year": "2006",
 "type": "قانون",
 "category": "اتفاقيات دولية",
 "isAmendment": false,
 "source_url": "https://www.cocayemen.com/laws/60",
 "source_format": "pdf",
 "scraped_at": "2026-07-02T18:14:51.518Z",
 "preamble": "‫قانون رقم (‪ )41‬لسنة ‪6002‬م‬\n‫بشأن الموافقة على بروتوكول بازل بشأن المسؤولية والتعويض عن الضرر الناجم‬\n‫عن نقل النفايات الخطرة والتخلص منها عبر الحدود‬\n‫باسم الشعب‪.‬‬\n‫رئيس الجمهورية‪:‬‬\n‫بعد الإطلاع على دستور الجمهورية اليمنية‪.‬‬\n‫وبعد موافقة مجلس الوزراء ومجلس النواب‪.‬‬\n‫أصدرنا القانون الآتي نصه‪-:‬‬\n‫مادة (‪ )1‬ووفق على بروتوكول بازل بشأن المسؤولية والتعويض عن الضرر الناجم عن نقل‬\n‫النفايات الخطرة والتخلص منها عبر الحدود المعتمد بتاريخ ‪1111/11/11‬م (المرافق لهذا‬\n‫القانون)‪.‬‬\n‫مادة (‪ )1‬يعمل بهذا القانون من تاريخ صدوره وينشر في الجريدة الرسمية‪.‬‬\n\n‫صدر برئاسة الجمهورية ‪ -‬بصنعاء‬\n‫بتاريخ ‪ / 62‬ربيع ثاني‪4161 /‬ه‬\n‫الموافق ‪ / 61‬مايو‪6002 /‬م‬\n‫علي عبد الله صالح‬\n‫رئيس الجمهورية‬",
 "articles": []
}